[{"name":"/#Artist Info/Artist Info","nodes":[{"id":"3e4fe803-6bc8-79da-4894-8a29e164759f","type":"Page","parameters":{},"ports":[],"children":[{"id":"481eb6fe-8235-ff18-d7aa-8947521cba2a","type":"Group","variant":"Page Container","parameters":{"flexDirection":"column","paddingTop":{"value":24,"unit":"px"},"clip":true,"sizeMode":"explicit","scrollEnabled":true,"justifyContent":"flex-start","paddingRight":{"value":24,"unit":"px"},"paddingLeft":{"value":24,"unit":"px"}},"stateParameters":{},"stateTransitions":{},"defaultStateTransitions":{},"ports":[],"children":[{"id":"8b132bc6-eee7-4b61-0118-2055391ecd74","type":"/#Artist Info/Artist Info View","parameters":{},"ports":[],"children":[]}]}]},{"id":"58cab2c7-86fa-51d5-4ea1-9be62f5ae90e","type":"PageInputs","parameters":{"pathParams":"Artist Id"},"ports":[],"children":[]}],"connections":[{"sourceId":"58cab2c7-86fa-51d5-4ea1-9be62f5ae90e","sourcePort":"pm-Artist Id","targetId":"8b132bc6-eee7-4b61-0118-2055391ecd74","targetPort":"Artist Id"}],"ports":[],"roots":["3e4fe803-6bc8-79da-4894-8a29e164759f"],"metadata":{"canvasPos":{"x":9582.030547035196,"y":-387.6882828614094}}},{"name":"/#Artist Info/Artist Info View","nodes":[{"id":"6c57b655-7e9f-514f-d878-f83d878c7612","type":"Group","parameters":{},"ports":[],"children":[{"id":"4d01f228-4802-55ca-e3b3-72b9048aa1b7","type":"/Components/Header2","parameters":{},"ports":[],"children":[]},{"id":"2fd42a33-b3f7-5115-9c6f-bc7f0a77f2e9","type":"Text","parameters":{"color":"Grey - 400","marginTop":{"value":0,"unit":"px"},"marginBottom":{"value":10,"unit":"px"}},"ports":[],"children":[]},{"id":"83f246ce-c595-afc4-f685-1a83a223a133","type":"Group","parameters":{},"ports":[],"children":[{"id":"5ed4005d-1d7c-f4af-7722-bb5ccf709f3f","type":"/Post Table","parameters":{"Headers":"[{\n    \"Field\":\"name\",\n    \"Label\":\"Track\",\n    \"Type\":\"Track\"\n  },\n  {\n    \"Field\":\"posts\",\n    \"Label\":\"Posts\",\n    \"Type\":\"Posts\"\n  }\n  ]","CurrentSortingField":"published","SortingDescending":true},"ports":[],"children":[]}]}]},{"id":"66e7914d-74cc-dad6-becf-f1b8ed26185a","type":"Component Inputs","parameters":{},"ports":[],"children":[]},{"id":"674a040c-5669-cd9e-c8ec-5c556c51f701","type":"DbModel2","parameters":{"collectionName":"SpotifyArtist"},"ports":[],"children":[]},{"id":"1346d6f3-cd61-f477-e1e1-b6822fc9dbd7","type":"DbCollection2","parameters":{"collectionName":"SpotifyTrack","visualFilter":{"combinator":"or","rules":[{"combinator":"and","rules":[{}]}]},"storageFilterType":"json","storageJSONFilter":"\n// Write your query script here, check out the reference documentation for examples\nconst relatedArtist = Inputs.ArtistId;\nwhere({artists:{pointsTo:relatedArtist} });\n"},"ports":[],"children":[]},{"id":"100f5dc4-fe37-93a0-560f-6571555d2c14","type":"String Format","parameters":{"format":"{count} tracks"},"ports":[],"children":[]},{"id":"c93e78e2-4303-61e5-b83a-2de3833155f9","type":"RouterNavigate","parameters":{"router":"main","target":"/#Track Info/Track Info"},"ports":[],"children":[]},{"id":"e7b906d3-bc5c-18ea-0660-1885f4bc9083","type":"Switch","parameters":{},"ports":[],"children":[]}],"connections":[{"sourceId":"66e7914d-74cc-dad6-becf-f1b8ed26185a","sourcePort":"Artist Id","targetId":"674a040c-5669-cd9e-c8ec-5c556c51f701","targetPort":"modelId"},{"sourceId":"674a040c-5669-cd9e-c8ec-5c556c51f701","sourcePort":"prop-name","targetId":"4d01f228-4802-55ca-e3b3-72b9048aa1b7","targetPort":"Title Text"},{"sourceId":"674a040c-5669-cd9e-c8ec-5c556c51f701","sourcePort":"id","targetId":"1346d6f3-cd61-f477-e1e1-b6822fc9dbd7","targetPort":"storageFilterValue-ArtistId"},{"sourceId":"100f5dc4-fe37-93a0-560f-6571555d2c14","sourcePort":"formatted","targetId":"2fd42a33-b3f7-5115-9c6f-bc7f0a77f2e9","targetPort":"text"},{"sourceId":"1346d6f3-cd61-f477-e1e1-b6822fc9dbd7","sourcePort":"count","targetId":"100f5dc4-fe37-93a0-560f-6571555d2c14","targetPort":"count"},{"sourceId":"6c57b655-7e9f-514f-d878-f83d878c7612","sourcePort":"didMount","targetId":"1346d6f3-cd61-f477-e1e1-b6822fc9dbd7","targetPort":"storageFetch"},{"sourceId":"1346d6f3-cd61-f477-e1e1-b6822fc9dbd7","sourcePort":"items","targetId":"5ed4005d-1d7c-f4af-7722-bb5ccf709f3f","targetPort":"Items"},{"sourceId":"5ed4005d-1d7c-f4af-7722-bb5ccf709f3f","sourcePort":"Item Id","targetId":"c93e78e2-4303-61e5-b83a-2de3833155f9","targetPort":"pm-TrackId"},{"sourceId":"5ed4005d-1d7c-f4af-7722-bb5ccf709f3f","sourcePort":"Item Clicked","targetId":"c93e78e2-4303-61e5-b83a-2de3833155f9","targetPort":"navigate"},{"sourceId":"1346d6f3-cd61-f477-e1e1-b6822fc9dbd7","sourcePort":"fetched","targetId":"e7b906d3-bc5c-18ea-0660-1885f4bc9083","targetPort":"on"},{"sourceId":"e7b906d3-bc5c-18ea-0660-1885f4bc9083","sourcePort":"state","targetId":"83f246ce-c595-afc4-f685-1a83a223a133","targetPort":"mounted"},{"sourceId":"6c57b655-7e9f-514f-d878-f83d878c7612","sourcePort":"didMount","targetId":"674a040c-5669-cd9e-c8ec-5c556c51f701","targetPort":"fetch"}],"ports":[{"name":"Artist Id","type":{"name":"string","allowConnectionsOnly":true},"group":"General","plug":"input","index":1}],"roots":["6c57b655-7e9f-514f-d878-f83d878c7612"],"metadata":{"canvasPos":{"x":8194.45422596137,"y":-472.3494868882634}}}]